.gitignore
MANIFEST.in
README.rst
setup.py
validation-files.yaml
validation-options.yaml
docs/HISTORY.txt
visualtitle/__init__.py
visualtitle/configure.zcml
visualtitle/extender.py
visualtitle/interfaces.py
visualtitle/updatetranslations.sh
visualtitle/views.py
visualtitle.egg-info/PKG-INFO
visualtitle.egg-info/SOURCES.txt
visualtitle.egg-info/dependency_links.txt
visualtitle.egg-info/entry_points.txt
visualtitle.egg-info/requires.txt
visualtitle.egg-info/top_level.txt
visualtitle/locales/README.txt
visualtitle/locales/visualtitle.pot
visualtitle/locales/en/LC_MESSAGES/visualtitle.mo
visualtitle/locales/en/LC_MESSAGES/visualtitle.po
visualtitle/locales/fi/LC_MESSAGES/visualtitle.mo
visualtitle/locales/fi/LC_MESSAGES/visualtitle.po
visualtitle/profiles/default/browserlayer.xml
visualtitle/profiles/default/cssregistry.xml
visualtitle/profiles/default/skins.xml
visualtitle/skins/visualtitle/kss_generic_macros.pt
visualtitle/static/main.css
visualtitle/templates/README.txt