Metadata-Version: 1.1
Name: visualtitle
Version: 0.3
Summary: Separate content and navigation titles for Plone CMS
Home-page: http://opensourcehacker.com
Author: Mikko Ohtamaa
Author-email: mikko@opensourcehacker.com
License: GPL2
Platform: UNKNOWN
Classifier: Framework :: Plone
Classifier: Programming Language :: Python
